apppy/fs/__init__.py
apppy/fs/errors.py
apppy/fs/fixtures.py
apppy/fs/fs_test.py
apppy/fs/fs_unit_test.py
apppy/fs/hash.py
apppy/fs/local.py
apppy/fs/local_test.py
apppy/fs/local_unit_test.py
apppy/fs/test_examples/quick_brown_fox.txt
apppy_fs-0.23.2.dist-info/METADATA
apppy_fs-0.23.2.dist-info/WHEEL
apppy_fs-0.23.2.dist-info/RECORD
