Metadata-Version: 2.4
Name: apppy-fs
Version: 0.23.2
Summary: Python filesystem definitions for server development
Project-URL: Homepage, https://github.com/spals/apppy
Author: Tim Kral
License: MIT
Classifier: License :: OSI Approved :: MIT License
Classifier: Programming Language :: Python :: 3
Requires-Python: >=3.11
Requires-Dist: apppy-env>=0.23.2
Requires-Dist: apppy-fastql>=0.23.2
Requires-Dist: apppy-generic>=0.23.2
Requires-Dist: apppy-logger>=0.23.2
Requires-Dist: fsspec==2025.9.0
Requires-Dist: s3fs==2025.9.0
